trainwave_cli/__init__.py
trainwave_cli/api.py
trainwave_cli/cli/auth.py
trainwave_cli/cli/jobs.py
trainwave_cli/cli/logs.py
trainwave_cli/cli/offers.py
trainwave_cli/cli/secrets.py
trainwave_cli/cli/setup.py
trainwave_cli/config/config.py
trainwave_cli/format_utils.py
trainwave_cli/io.py
trainwave_cli/main.py
trainwave_cli/utils.py
trainwave_cli/xceptions.py
trainwave_cli-0.2.8.dist-info/METADATA
trainwave_cli-0.2.8.dist-info/WHEEL
trainwave_cli-0.2.8.dist-info/entry_points.txt
trainwave_cli-0.2.8.dist-info/RECORD
