Metadata-Version: 2.3
Name: trainwave-cli
Version: 0.2.8
Summary: Trainwave CLI - A command-line interface for managing Trainwave resources
License: MIT
Keywords: cli,trainwave,ai,machine-learning
Author: Johan Backman
Author-email: johan@trainwave.ai
Maintainer: Johan Backman
Maintainer-email: johan@trainwave.ai
Requires-Python: >=3.10,<4.0
Classifier: Development Status :: 4 - Beta
Classifier: Environment :: Console
Classifier: Intended Audience :: Developers
Classifier: Intended Audience :: Science/Research
Classifier: License :: OSI Approved :: MIT License
Classifier: Operating System :: OS Independent
Classifier: Programming Language :: Python :: 3
Classifier: Programming Language :: Python :: 3.10
Classifier: Programming Language :: Python :: 3.11
Classifier: Programming Language :: Python :: 3.12
Classifier: Programming Language :: Python :: 3.13
Classifier: Topic :: Scientific/Engineering :: Artificial Intelligence
Classifier: Topic :: Software Development :: Libraries :: Python Modules
Requires-Dist: aiofiles (>=24.1.0,<25.0.0)
Requires-Dist: aiohttp (>=3.10,<4.0)
Requires-Dist: beaupy (>=3.9.2,<4.0.0)
Requires-Dist: boto3 (>=1.30)
Requires-Dist: dacite (>=1.9.2,<2.0.0)
Requires-Dist: httpx (==0.28.1)
Requires-Dist: human-readable (>=1.3.4,<2.0.0)
Requires-Dist: loguru (>=0.7.2,<0.8.0)
Requires-Dist: pathspec (>=0.12.1,<0.13.0)
Requires-Dist: pytimeparse (>=1.1.8,<2.0.0)
Requires-Dist: tabulate (>=0.9.0,<0.10.0)
Requires-Dist: toml (>=0.10.2,<0.11.0)
Requires-Dist: tqdm (>=4.66.4,<5.0.0)
Requires-Dist: typer (>=0.12.5,<0.13.0)
Requires-Dist: typer-config[all] (>=1.4.0,<2.0.0)
Requires-Dist: websockets (>=12.0,<13.0)
Project-URL: Documentation, https://trainwave.ai/docs
Project-URL: Homepage, https://trainwave.ai
